hwdesk/__init__.py
hwdesk/__main__.py
hwdesk/constants.py
hwdesk/gui.py
hwdesk/logger.py
hwdesk/py.typed
hwdesk/camera/__init__.py
hwdesk/camera/base.py
hwdesk/camera/ms2109.py
hwdesk/camera/ms2130.py
hwdesk/camera/prompt.py
hwdesk/controls/__init__.py
hwdesk/controls/ch9329.py
hwdesk/controls/prompt.py
hwdesk-1.0.6.dist-info/LICENSE
hwdesk-1.0.6.dist-info/METADATA
hwdesk-1.0.6.dist-info/WHEEL
hwdesk-1.0.6.dist-info/entry_points.txt
hwdesk-1.0.6.dist-info/top_level.txt
hwdesk-1.0.6.dist-info/RECORD
