Metadata-Version: 2.1
Name: hwdesk
Version: 1.0.6
Author-email: Pradish Bijukchhe <pradish@sandbox.com.np>
License: Copyright (c) 2018 The Python Packaging Authority
Project-URL: Homepage, https://github.com/sandbox-pokhara/hwdesk
Project-URL: Issues, https://github.com/sandbox-pokhara/hwdesk/issues
Classifier: Programming Language :: Python :: 3
Requires-Python: >=3.11
License-File: LICENSE
Requires-Dist: ch9329 >=1.2.1
Requires-Dist: keyboard ==0.13.5
Requires-Dist: opencv-cam-idx ==1.0.1
Requires-Dist: opencv-contrib-python ==4.9.0.80
Requires-Dist: pillow ==10.3.0
Requires-Dist: pydantic ==2.6.4
